organize_stream/__init__.py
organize_stream/__main__.py
organize_stream/cartas/__init__.py
organize_stream/cartas/carta_calculo.py
organize_stream/document/__init__.py
organize_stream/document/name_files.py
organize_stream/erros/__init__.py
organize_stream/find/__init__.py
organize_stream/find/find_names.py
organize_stream/read/__init__.py
organize_stream/text_extract/__init__.py
organize_stream/text_extract/text_extract.py
organize_stream/type_utils/__init__.py
organize_stream/type_utils/digital_doc.py
organize_stream/type_utils/keyword_files.py
organize_stream/type_utils/observer.py
organize_stream/utils/__init__.py
organize_stream-2.5.7.dist-info/METADATA
organize_stream-2.5.7.dist-info/WHEEL
organize_stream-2.5.7.dist-info/top_level.txt
organize_stream-2.5.7.dist-info/RECORD
