Metadata-Version: 2.4
Name: organize_stream
Version: 2.5.7
Summary: Organizar documentos PDF e imagens.
Author: Bruno Chaves
Requires-Python: >=3.11
Requires-Dist: soup_files>=1.4.2
Requires-Dist: PyMuPDF
Requires-Dist: convert_stream>=2.5.1
Requires-Dist: sheet_stream>=0.1.3
Requires-Dist: ocr_stream>=2.5.2
Requires-Dist: pandas
Requires-Dist: opencv-python
Requires-Dist: pytesseract
